.gitignore
.gitlab-ci.yml
COPYING
MANIFEST.in
README.md
requirements.txt
setup.py
tox.ini
derezzed/__init__.py
derezzed/geo.py
derezzed/ip.py
derezzed/rechain.py
derezzed/useragent.py
derezzed.egg-info/PKG-INFO
derezzed.egg-info/SOURCES.txt
derezzed.egg-info/dependency_links.txt
derezzed.egg-info/requires.txt
derezzed.egg-info/top_level.txt
derezzed/tests/GeoIP2-City-Test.mmdb
derezzed/tests/__init__.py
derezzed/tests/ma.geojson
derezzed/tests/test_geo.py
derezzed/tests/test_ip.py
derezzed/tests/test_useragent.py
derezzed/tests/usa.geojson
docs/Makefile
docs/conf.py
docs/geo.rst
docs/index.rst
docs/ip.rst
docs/rechain.rst
docs/useragent.rst
docs/_static/logo.png